setup.py
ip_intelligence.egg-info/PKG-INFO
ip_intelligence.egg-info/SOURCES.txt
ip_intelligence.egg-info/dependency_links.txt
ip_intelligence.egg-info/not-zip-safe
ip_intelligence.egg-info/requires.txt
ip_intelligence.egg-info/top_level.txt
src/__init__.py
src/check_json.py
src/city_data.py
src/client.py
src/connection.py
src/country_data.py
src/domain.py
src/ip_lookup.py
src/location.py
src/network.py
src/organization_data.py
src/proxy_data.py
src/state_data.py