Metadata-Version: 1.1
Name: ip-intelligence
Version: 1.1
Summary: A Python library for the Neustar IP Intelligence API
Home-page: https://github.com/sbarbett/ip_intelligence
Author: Shane Barbetta
Author-email: shane@barbetta.me
License: Apache License, Version 2.0
Keywords: ip_intelligence
Platform: UNKNOWN
Classifier: Development Status :: 5 - Production/Stable
Classifier: Topic :: Utilities
Classifier: License :: OSI Approved :: Apache Software License
